tensorsense/__init__.py
tensorsense-0.1.0.dist-info/METADATA
tensorsense-0.1.0.dist-info/WHEEL
tensorsense-0.1.0.dist-info/licenses/LICENSE
tensorsense-0.1.0.dist-info/RECORD
