Metadata-Version: 2.3
Name: tensorsense
Version: 0.1.0
Summary: Add your description here
License-File: LICENSE
Requires-Python: >=3.12
Requires-Dist: transformers==4.44.2
